{"is_source_file": true, "format": "Dart", "description": "This file defines the WishlistScreen widget for a Flutter app, rendering a grid of wishlist books with a CTA for each book.", "external_files": ["package:flutter/material.dart", "package:mobile_app/app_router.dart", "package:mobile_app/data/mock_data.dart", "package:mobile_app/data/models.dart", "package:mobile_app/theme/theme.dart", "package:mobile_app/widgets/book_card.dart"], "external_methods": ["Navigator.pushNamed", "Theme.of", "ScaffoldMessenger.of", "ScaffoldMessenger.showSnackBar"], "published": ["WishlistScreen"], "classes": [{"name": "WishlistScreen", "description": "A stateless widget that displays a grid of wishlist books with a CTA button."}], "methods": [{"name": "_openProduct", "description": "Navigates to the product detail page for a given book using named routes."}, {"name": "build", "description": "Builds the widget tree for the wishlist screen, displaying the wishlist items in a grid."}], "calls": ["Navigator.pushNamed", "Theme.of", "ScaffoldMessenger.of", "ScaffoldMessenger.showSnackBar"], "search-terms": ["WishlistScreen", "book grid", "wishlist", "flutter gridview", "move to cart button", "wish list render"], "state": 2, "file_id": 89, "knowledge_revision": 213, "git_revision": "", "revision_history": [{"203": ""}, {"213": ""}], "hash": "07512a85af4e404ce5741de9086c5ccb", "format-version": 4, "code-base-name": "mobile_app", "filename": "mobile_app/lib/screens/wishlist_screen.dart"}